src/OpL/SlaveOpl.vhd
library ieee;
    use ieee.std_logic_1164.all;

entity SlaveOpl is
  port(
    sclk : in  std_logic;
    mosi : in  std_logic;
    miso : out std_logic;
    ss   : in  std_logic
  );
end SlaveOpl;

--------------------------------------------------------------------------------

architecture behavioral of SlaveOpl is

  signal v1 : std_logic_vector(7 downto 0) := (others => 'U');
  signal v2 : std_logic_vector(7 downto 0) := (others => 'U');
  -- les valeurs initiales de val_and, val_or et val_xor sont les valeurs émises
  -- lors de la première transmission
  signal val_and : std_logic_vector(7 downto 0) := "00110011";
  signal val_or  : std_logic_vector(7 downto 0) := "11001100";
  signal val_xor : std_logic_vector(7 downto 0) := "10100000";

  signal count_mosi     : natural;  -- bit index dans l'octet à recevoir
  signal num_octet_mosi : natural;  -- index de l'octet à recevoir

  signal count_miso     : natural;  -- bit index dans l'octet à envoyer
  signal num_octet_miso : natural;  -- index de l'octet à envoyer

begin

  -- process de capture des 3 octets sur front montant de sclk
  capture : process(ss, sclk)
  begin
    if ( ss = '1' ) then  -- ss est un reset asynchrone
      count_mosi     <= 7;
      num_octet_mosi <= 0;
    elsif ( rising_edge(sclk) ) then
      case (num_octet_mosi) is
        when 0 =>
          v1(count_mosi) <= mosi;
          --
          if ( count_mosi > 0 ) then
            count_mosi <= count_mosi - 1;
          else
            count_mosi     <= 7;
            num_octet_mosi <= num_octet_mosi + 1;
          end if;

        when 1 =>
          v2(count_mosi) <= mosi;
          --
          if ( count_mosi > 0 ) then
            count_mosi <= count_mosi - 1;
          else
            count_mosi     <= 7;
            num_octet_mosi <= num_octet_mosi + 1;
          end if;

        when others =>
          if ( count_mosi > 0 ) then
            count_mosi <= count_mosi - 1;
          else
            count_mosi     <= 7;
            num_octet_mosi <= 0;
            --
            val_and <= v1 and v2;
            val_or  <= v1 or  v2;
            val_xor <= v1 xor v2;
          end if;
      end case;
    end if;
  end process;


  -- process de "présentation" des 3 octets : val_and, val_or et val_xor
  envoi : process(ss, sclk)
  begin
    if ( ss = '1' ) then  -- ss est un reset asynchrone
      count_miso     <= 7;
      num_octet_miso <= 0;
    elsif ( falling_edge(sclk) ) then
      case (num_octet_miso) is
        when 0 =>
          miso <= val_and(count_miso);
          --
          if ( count_miso > 0 ) then
            count_miso <= count_miso - 1;
          else
            count_miso     <= 7;
            num_octet_miso <= num_octet_miso + 1;
          end if;

        when 1 =>
          miso <= val_or(count_miso);
          --
          if ( count_miso > 0 ) then
            count_miso <= count_miso - 1;
          else
            count_miso     <= 7;
            num_octet_miso <= num_octet_miso + 1;
          end if;

        when others =>
          miso <= val_xor(count_miso);
          --
          if ( count_miso > 0 ) then
            count_miso <= count_miso - 1;
          else
            count_miso     <= 7;
            num_octet_miso <= 0;
          end if;
      end case;
    end if;
  end process;

end behavioral;

src/ER_1OCTET/er_1octet.vhd
library IEEE;
use IEEE.STD_LOGIC_1164.ALL;
use IEEE.std_logic_arith.all;
use IEEE.std_logic_unsigned.all;

entity er_1octet is
 port ( rst : in std_logic ;                        -- Bouton C pour reset (actif à ’0’)
        clk : in std_logic ;                        -- Horloge intégrée 100Mhz
        en : in std_logic ;                         -- Indique qu’un ordre d’échange (émission/réception) d’1 octet est passé (actif à ’1’)
        din : in std_logic_vector (7 downto 0);     -- L'octet à émettre
        miso : in std_logic ;                       -- Master Input Slave Output (produit par l'esclave)
        sclk : out std_logic ;                      -- Serial clock (produit par le maître)
        mosi : out std_logic ;                      -- Master Output Slave Input (produit par le maître)
        dout : out std_logic_vector (7 downto 0) ;  -- L'octet reçu une fois l’émission/réception terminée
        busy : out std_logic);                      -- Indique que le composant est occupé à émettre/réceptionner (actif à ’1’)
end er_1octet;

architecture behavioral_3 of er_1octet is

    -- États possibles lors de l'échange d'un octet
    type t_etat is (attente, capturer_bit, emettre_bit);
    
    -- État actuel
    signal etat : t_etat;

begin

     -- Échanger 1 octet
    er : process (clk, rst)
        
        
        variable cpt : integer range 0 to 7 := 0;
        variable registre : std_logic_vector (7 downto 0) := "00000000";
        
    begin

        if (rst = '0') then

            -- Retour dans l'état d'attente
            etat <= attente;
            sclk <= '1'; 
                
            -- Mise à zéro de tous les signaux et variables
            mosi <= '0';
            dout <= "00000000";
            busy <= '0';
            cpt := 0;
            registre := "00000000";

        elsif (rising_edge(clk)) then

            case etat is
                
                when attente =>
                    if (en = '1') then
                        busy <= '1';
                        sclk <= '0';
                        registre := din;        -- On copie din dans un registre car on a pas de garantie que din sera constant lors de la capture
                        cpt := 7;
                        mosi <= registre(cpt);	-- Pour ne pas perdre un cycle d'horloge on envoie le premier bit ici
                        etat <= capturer_bit;
                    end if; --en

                when capturer_bit =>
                    sclk <= '1';
                    registre(cpt) := miso;
                    if (cpt = 0) then
                        busy <= '0';
                        dout <= registre;
                        etat <= attente;
                    else -- cpt > 0
                        etat <= emettre_bit;
                    end if; --cpt
            
                when emettre_bit =>
                    cpt := cpt - 1;
                    mosi <= registre(cpt);
                    sclk <= '0';
                    etat <= capturer_bit;
            
            end case; --etat
        end if; --reset

  end process;

end behavioral_3;

src/OpL/MasterOpl.vhd
library IEEE;
use IEEE.STD_LOGIC_1164.ALL;
use IEEE.std_logic_arith.all;
use IEEE.std_logic_unsigned.all;

entity MasterOpl is
  port ( rst : in std_logic;                            -- Bouton C pour reset (actif à ’0’)
         clk : in std_logic;                            -- Horloge intégrée 100Mhz
         en : in std_logic;                             -- Indique qu’un ordre d’échange (émission/réception) d’1 octet est passé (actif à ’1’)
         v1 : in std_logic_vector (7 downto 0);         -- 1er octet opérande
         v2 : in std_logic_vector(7 downto 0);          -- 2ème octet opérande
         miso : in std_logic;                           -- Master Input Slave Output (produit par l'esclave)
         ss   : out std_logic;                          -- Slave Select (actif à ’0’)
         sclk : out std_logic;                          -- Serial clock (produit par le maître)
         mosi : out std_logic;                          -- Master Output Slave Input (produit par le maître)
         val_and : out std_logic_vector (7 downto 0);   -- v1 and v2
         val_or : out std_logic_vector (7 downto 0);    -- v1 or v2
         val_xor : out std_logic_vector (7 downto 0);   -- v1 xor v2
         busy : out std_logic);                         -- Indique que le composant est occupé à émettre/réceptionner (actif à ’1’)
end MasterOpl;

architecture behavior of MasterOpl is

    -- Echange d'un octet
    component er_1octet port(
        rst : in std_logic ;
        clk : in std_logic ;
        en : in std_logic ;
        din : in std_logic_vector (7 downto 0);     -- L’octet à émettre, sa valeur est fournie au moment où le composant est au repos et enable passe à '1'
        miso : in std_logic ;
        sclk : out std_logic ;
        mosi : out std_logic ;
        dout : out std_logic_vector (7 downto 0);   -- L’octet reçu une fois l’émission/réception terminée
        busy : out std_logic
    );
    end component;
    
    -- L'octet à émettre (v1, v2, ou 0)
    signal din_er : std_logic_vector(7 downto 0) := (others => 'U');
    
    -- L’octet reçu une fois l’émission/réception terminée
    signal dout_er : std_logic_vector(7 downto 0) := (others => 'U');
    
    -- Indique que le composant est occupé à émettre/réceptionner (actif à ’1’)
    signal busy_er : std_logic;

    -- Entrée de er_1octet
    signal en_er : std_logic := '0';
    
    -- Etats possibles du Master
    type t_etat is (repos, attente, echange);

    -- Etat actuel
    signal etat : t_etat;
    
begin

    -- Emission et réception de chaque octet
    er_1octet_Inst: er_1octet port map(
        rst=>rst,
        clk=>clk,
        en=>en_er,
        din=>din_er,
        miso=>miso,
        sclk=>sclk,
        mosi=>mosi,
        dout=>dout_er,
        busy=>busy_er
    );
    

    -- Envoi des données à l'esclave et récupération des résultats
    master: process (clk, rst)
    
        -- Compteur décrémenté pendant l'attente
        variable cpt : natural := 0;
        
        -- Numéro de l'octet envoyé
        variable num_octet : natural := 0;
        
        -- Nombre d'octets total à envoyer
        constant NB_OCTETS : natural := 3;
        
        -- Nombre de cycles d'horloge nécessaire pour que l'esclave soit prêt
        constant ATTENTE_ESCLAVE : natural := 10;
        
        -- Nombre de cycles d'horloge à attendre avant l'envoi de l'octet suivant
        constant ATTENTE_ENVOI : natural := 2;
    
    begin

        if (rst = '0') then

            -- Réinitialiser les signaux
            etat <= repos;
            ss <= '1';
            val_and <= "00000000";
            val_or <= "00000000";
            val_xor <= "00000000";
            busy <= '0';
						en_er <= '0';

        elsif (rising_edge(clk)) then
    
            case (etat) is
            
                when repos =>

                    if (en = '1') then
                    -- Un ordre a été passé au composant
                        ss <= '0';                      -- Initialiser la transmission
                        busy <= '1';                    -- Indiquer que le composant est occupé
                        cpt := ATTENTE_ESCLAVE;         -- Attendre que l'esclave soit prêt
                        num_octet := 0;
                        etat <= attente;
                        
                    end if;                             -- Le composant n'est pas actif, on reste en repos

                when attente =>
                
                    if (cpt = 0) then                   -- Fin de l'attente
                        case num_octet is
                            when 0 =>
                                din_er <= v1;           -- Envoi du 1er octet
                            when 1 =>
                                din_er <= v2;           -- Envoi du 2ème octet
                            when others => null;
                        end case;
                        
                        en_er <= '1';                   -- Activer er_1octet pour échanger l'octet
                        etat <= echange;
                        
                    else
                        cpt := cpt - 1;                 -- On reste en attente
                        
                    end if;
                        
                when echange =>
                    if (busy_er = '0' and en_er = '0') then  -- On vérifie que er_1octet a bien terminé son échange
                        case num_octet is
                            when 0 =>
                                val_and <= dout_er;     -- Réception du 1er octet
                                etat <= attente;
                            when 1 =>
                                val_or <= dout_er;      -- Réception du 2ème octet
                                etat <= attente;
                            when 2 =>
                                val_xor <= dout_er;     -- Réception du 3ème octet
                                ss <= '1';              -- Terminer la transmission
                                busy <= '0';            -- Le maitre n'est plus occupé
                                etat <= repos;          -- Retour dans l'état repos jusqu'à la prochaine transmission
                                en_er <= '0';           -- Fin de l'échange, on peut désactiver er_1octet
                            when others => null;
                        end case;
                    
                        num_octet := num_octet + 1;
                        cpt := ATTENTE_ENVOI;           -- Attendre avant l'échange du prochain octet
                            
                    else
                        en_er <= '0';                   -- Nécessaire pour différencier le début et la fin d'un échange
                    end if;
                    
            end case;
            
        end if;
    
    end process;

end behavior;

src/OpL/TestOpl.vhd
--------------------------------------------------------------------------------
-- Company: 
-- Engineer:
--
-- Create Date:   11:15:05 11/19/2020
-- Design Name:   
-- Module Name:   /home/tpillot/2SN/Archi/mini_projet/src/OpL/TestOpl.vhd
-- Project Name:  MasterOPL
-- Target Device:  
-- Tool versions:  
-- Description:   
-- 
-- VHDL Test Bench Created by ISE for module: MasterOpl
-- 
-- Dependencies:
-- 
-- Revision:
-- Revision 0.01 - File Created
-- Additional Comments:
--
-- Notes: 
-- This testbench has been automatically generated using types std_logic and
-- std_logic_vector for the ports of the unit under test.  Xilinx recommends
-- that these types always be used for the top-level I/O of a design in order
-- to guarantee that the testbench will bind correctly to the post-implementation 
-- simulation model.
--------------------------------------------------------------------------------
LIBRARY ieee;
USE ieee.std_logic_1164.ALL;
 
-- Uncomment the following library declaration if using
-- arithmetic functions with Signed or Unsigned values
--USE ieee.numeric_std.ALL;
 
ENTITY TestOpl IS
END TestOpl;
 
ARCHITECTURE behavior OF TestOpl IS 
 
    -- Component Declaration for the Unit Under Test (UUT)
 
    COMPONENT MasterOpl
    PORT(
         rst : IN  std_logic;
         clk : IN  std_logic;
         en : IN  std_logic;
         v1 : IN  std_logic_vector(7 downto 0);
         v2 : IN  std_logic_vector(7 downto 0);
         miso : IN  std_logic;
         ss : OUT  std_logic;
         sclk : OUT  std_logic;
         mosi : OUT  std_logic;
         val_and : OUT  std_logic_vector(7 downto 0);
         val_or : OUT  std_logic_vector(7 downto 0);
         val_xor : OUT  std_logic_vector(7 downto 0);
         busy : OUT  std_logic
        );
    END COMPONENT;
    
    COMPONENT SlaveOpl
		PORT(
			sclk : IN std_logic;
			mosi : IN std_logic;
			ss : IN std_logic;          
			miso : OUT std_logic
			);
		END COMPONENT;

   --Inputs
   signal rst : std_logic := '0';
   signal clk : std_logic := '0';
   signal en : std_logic := '0';
   signal v1 : std_logic_vector(7 downto 0) := (others => '0');
   signal v2 : std_logic_vector(7 downto 0) := (others => '0');
   signal miso : std_logic := '0';

 	--Outputs
   signal ss : std_logic;
   signal sclk : std_logic;
   signal mosi : std_logic;
   signal val_and : std_logic_vector(7 downto 0);
   signal val_or : std_logic_vector(7 downto 0);
   signal val_xor : std_logic_vector(7 downto 0);
   signal busy : std_logic;

   -- Clock period definitions
   constant clk_period : time := 10 ns;
 
BEGIN
 
	-- Instantiate the Unit Under Test (UUT)
   uut: MasterOpl PORT MAP (
          rst => rst,
          clk => clk,
          en => en,
          v1 => v1,
          v2 => v2,
          miso => miso,
          ss => ss,
          sclk => sclk,
          mosi => mosi,
          val_and => val_and,
          val_or => val_or,
          val_xor => val_xor,
          busy => busy
        );
				
	Inst_SlaveOpl: SlaveOpl PORT MAP(
		sclk => sclk,
		mosi => mosi,
		miso => miso,
		ss => ss
		);

   -- Clock process definitions
   clk_process :process
   begin
		clk <= '0';
		wait for clk_period/2;
		clk <= '1';
		wait for clk_period/2;
   end process;

   -- Stimulus process
   stim_proc: process
   begin		
      -- hold reset state for 100 ns.
			rst <= '0';
      wait for 100 ns;
			rst <= '1';

      wait for clk_period*10;

      -- insert stimulus here
			
			-- test 1 : val_and = "00000000", val_or = "11111111", val_xor = "11111111"
			v1 <= "00000000";
			v2 <= "11111111";
			en <= '1';						 -- Début de l'échange entre le maître et l'esclave
			
			wait until busy = '1'; -- On attend que l'échange commence
			en <= '0';						 -- On désactive le composant
			
			-- Arrivée des valeurs initiales de val_and, val_or et val_xor
			
			wait until busy = '0'; -- On attend que l'échange se termine avant le test suivant
			
			-- test 2 : val_and = "01000000", val_or = "11111011", val_xor = "10111011"
			v1 <= "11010001";
			v2 <= "01101010";
			en <= '1';
			
			wait until busy = '1';
			en <= '0';
			
			-- Arrivée des valeurs de val_and, val_or et val_xor du test 1
			
			wait until busy = '0';
			
			en <= '1';
			
			wait until busy = '1';
			en <= '0';
			
			-- Arrivée des valeurs de val_and, val_or et val_xor du test 2

      wait;
   end process;

END;

src/OpL/output.vcd
$date
   Thu Nov 19 22:32:19 2020
$end
$version
  P.20131013
$end
$timescale
  1ps
$end
$scope module testopl $end
$var wire 1 6! rst $end
$var wire 1 7! clk $end
$var wire 1 S en $end
$var wire 1 [ v1 [7] $end
$var wire 1 Z v1 [6] $end
$var wire 1 Y v1 [5] $end
$var wire 1 X v1 [4] $end
$var wire 1 W v1 [3] $end
$var wire 1 V v1 [2] $end
$var wire 1 U v1 [1] $end
$var wire 1 T v1 [0] $end
$var wire 1 c v2 [7] $end
$var wire 1 b v2 [6] $end
$var wire 1 a v2 [5] $end
$var wire 1 ` v2 [4] $end
$var wire 1 _ v2 [3] $end
$var wire 1 ^ v2 [2] $end
$var wire 1 ] v2 [1] $end
$var wire 1 \ v2 [0] $end
$var wire 1 P! miso $end
$var wire 1 Q! ss $end
$var wire 1 N! sclk $end
$var wire 1 O! mosi $end
$var wire 1 o val_and [7] $end
$var wire 1 n val_and [6] $end
$var wire 1 m val_and [5] $end
$var wire 1 l val_and [4] $end
$var wire 1 k val_and [3] $end
$var wire 1 j val_and [2] $end
$var wire 1 i val_and [1] $end
$var wire 1 h val_and [0] $end
$var wire 1 w val_or [7] $end
$var wire 1 v val_or [6] $end
$var wire 1 u val_or [5] $end
$var wire 1 t val_or [4] $end
$var wire 1 s val_or [3] $end
$var wire 1 r val_or [2] $end
$var wire 1 q val_or [1] $end
$var wire 1 p val_or [0] $end
$var wire 1 !! val_xor [7] $end
$var wire 1 ~ val_xor [6] $end
$var wire 1 } val_xor [5] $end
$var wire 1 | val_xor [4] $end
$var wire 1 { val_xor [3] $end
$var wire 1 z val_xor [2] $end
$var wire 1 y val_xor [1] $end
$var wire 1 x val_xor [0] $end
$var wire 1 "! busy $end
$scope module uut $end
$var wire 1 6! rst $end
$var wire 1 7! clk $end
$var wire 1 S en $end
$var wire 1 [ v1 [7] $end
$var wire 1 Z v1 [6] $end
$var wire 1 Y v1 [5] $end
$var wire 1 X v1 [4] $end
$var wire 1 W v1 [3] $end
$var wire 1 V v1 [2] $end
$var wire 1 U v1 [1] $end
$var wire 1 T v1 [0] $end
$var wire 1 c v2 [7] $end
$var wire 1 b v2 [6] $end
$var wire 1 a v2 [5] $end
$var wire 1 ` v2 [4] $end
$var wire 1 _ v2 [3] $end
$var wire 1 ^ v2 [2] $end
$var wire 1 ] v2 [1] $end
$var wire 1 \ v2 [0] $end
$var wire 1 P! miso $end
$var wire 1 Q! ss $end
$var wire 1 N! sclk $end
$var wire 1 O! mosi $end
$var wire 1 o val_and [7] $end
$var wire 1 n val_and [6] $end
$var wire 1 m val_and [5] $end
$var wire 1 l val_and [4] $end
$var wire 1 k val_and [3] $end
$var wire 1 j val_and [2] $end
$var wire 1 i val_and [1] $end
$var wire 1 h val_and [0] $end
$var wire 1 w val_or [7] $end
$var wire 1 v val_or [6] $end
$var wire 1 u val_or [5] $end
$var wire 1 t val_or [4] $end
$var wire 1 s val_or [3] $end
$var wire 1 r val_or [2] $end
$var wire 1 q val_or [1] $end
$var wire 1 p val_or [0] $end
$var wire 1 !! val_xor [7] $end
$var wire 1 ~ val_xor [6] $end
$var wire 1 } val_xor [5] $end
$var wire 1 | val_xor [4] $end
$var wire 1 { val_xor [3] $end
$var wire 1 z val_xor [2] $end
$var wire 1 y val_xor [1] $end
$var wire 1 x val_xor [0] $end
$var wire 1 "! busy $end
$var wire 1 @! din_er [7] $end
$var wire 1 ?! din_er [6] $end
$var wire 1 >! din_er [5] $end
$var wire 1 =! din_er [4] $end
$var wire 1 <! din_er [3] $end
$var wire 1 ;! din_er [2] $end
$var wire 1 :! din_er [1] $end
$var wire 1 9! din_er [0] $end
$var wire 1 K! dout_er [7] $end
$var wire 1 J! dout_er [6] $end
$var wire 1 I! dout_er [5] $end
$var wire 1 H! dout_er [4] $end
$var wire 1 G! dout_er [3] $end
$var wire 1 F! dout_er [2] $end
$var wire 1 E! dout_er [1] $end
$var wire 1 D! dout_er [0] $end
$var wire 1 L! busy_er $end
$var wire 1 8! en_er $end
$scope module er_1octet_Inst $end
$var wire 1 6! rst $end
$var wire 1 7! clk $end
$var wire 1 8! en $end
$var wire 1 @! din [7] $end
$var wire 1 ?! din [6] $end
$var wire 1 >! din [5] $end
$var wire 1 =! din [4] $end
$var wire 1 <! din [3] $end
$var wire 1 ;! din [2] $end
$var wire 1 :! din [1] $end
$var wire 1 9! din [0] $end
$var wire 1 P! miso $end
$var wire 1 N! sclk $end
$var wire 1 O! mosi $end
$var wire 1 K! dout [7] $end
$var wire 1 J! dout [6] $end
$var wire 1 I! dout [5] $end
$var wire 1 H! dout [4] $end
$var wire 1 G! dout [3] $end
$var wire 1 F! dout [2] $end
$var wire 1 E! dout [1] $end
$var wire 1 D! dout [0] $end
$var wire 1 L! busy $end
$upscope $end
$upscope $end
$scope module Inst_SlaveOpl $end
$var wire 1 N! sclk $end
$var wire 1 O! mosi $end
$var wire 1 P! miso $end
$var wire 1 Q! ss $end
$var wire 1 Y! v1 [7] $end
$var wire 1 X! v1 [6] $end
$var wire 1 W! v1 [5] $end
$var wire 1 V! v1 [4] $end
$var wire 1 U! v1 [3] $end
$var wire 1 T! v1 [2] $end
$var wire 1 S! v1 [1] $end
$var wire 1 R! v1 [0] $end
$var wire 1 a! v2 [7] $end
$var wire 1 `! v2 [6] $end
$var wire 1 _! v2 [5] $end
$var wire 1 ^! v2 [4] $end
$var wire 1 ]! v2 [3] $end
$var wire 1 \! v2 [2] $end
$var wire 1 [! v2 [1] $end
$var wire 1 Z! v2 [0] $end
$var wire 1 i! val_and [7] $end
$var wire 1 h! val_and [6] $end
$var wire 1 g! val_and [5] $end
$var wire 1 f! val_and [4] $end
$var wire 1 e! val_and [3] $end
$var wire 1 d! val_and [2] $end
$var wire 1 c! val_and [1] $end
$var wire 1 b! val_and [0] $end
$var wire 1 q! val_or [7] $end
$var wire 1 p! val_or [6] $end
$var wire 1 o! val_or [5] $end
$var wire 1 n! val_or [4] $end
$var wire 1 m! val_or [3] $end
$var wire 1 l! val_or [2] $end
$var wire 1 k! val_or [1] $end
$var wire 1 j! val_or [0] $end
$var wire 1 y! val_xor [7] $end
$var wire 1 x! val_xor [6] $end
$var wire 1 w! val_xor [5] $end
$var wire 1 v! val_xor [4] $end
$var wire 1 u! val_xor [3] $end
$var wire 1 t! val_xor [2] $end
$var wire 1 s! val_xor [1] $end
$var wire 1 r! val_xor [0] $end
$upscope $end
$upscope $end
$enddefinitions $end
#0
$dumpvars
07!
06!
0S
0[
0Z
0Y
0X
0W
0V
0U
0T
0c
0b
0a
0`
0_
0^
0]
0\
xP!
1Q!
1N!
0O!
0o
0n
0m
0l
0k
0j
0i
0h
0w
0v
0u
0t
0s
0r
0q
0p
0!!
0~
0}
0|
0{
0z
0y
0x
0"!
x@!
x?!
x>!
x=!
x<!
x;!
x:!
x9!
0K!
0J!
0I!
0H!
0G!
0F!
0E!
0D!
0L!
08!
xY!
xX!
xW!
xV!
xU!
xT!
xS!
xR!
xa!
x`!
x_!
x^!
x]!
x\!
x[!
xZ!
0i!
0h!
1g!
1f!
0e!
0d!
1c!
1b!
1q!
1p!
0o!
0n!
1m!
1l!
0k!
0j!
1y!
0x!
1w!
0v!
0u!
0t!
0s!
0r!
$end
#5000
17!
#10000
07!
#15000
17!
#20000
07!
#25000
17!
#30000
07!
#35000
17!
#40000
07!
#45000
17!
#50000
07!
#55000
17!
#60000
07!
#65000
17!
#70000
07!
#75000
17!
#80000
07!
#85000
17!
#90000
07!
#95000
17!
#100000
07!
16!
#105000
17!
#110000
07!
#115000
17!
#120000
07!
#125000
17!
#130000
07!
#135000
17!
#140000
07!
#145000
17!
#150000
07!
#155000
17!
#160000
07!
#165000
17!
#170000
07!
#175000
17!
#180000
07!
#185000
17!
#190000
07!
#195000
17!
#200000
07!
1S
1c
1b
1a
1`
1_
1^
1]
1\
#205000
17!
0S
0Q!
1"!
#210000
07!
#215000
17!
#220000
07!
#225000
17!
#230000
07!
#235000
17!
#240000
07!
#245000
17!
#250000
07!
#255000
17!
#260000
07!
#265000
17!
#270000
07!
#275000
17!
#280000
07!
#285000
17!
#290000
07!
#295000
17!
#300000
07!
#305000
17!
#310000
07!
#315000
17!
0@!
0?!
0>!
0=!
0<!
0;!
0:!
09!
18!
#320000
07!
#325000
17!
0P!
0N!
1L!
08!
#330000
07!
#335000
17!
1N!
0Y!
#340000
07!
#345000
17!
0N!
#350000
07!
#355000
17!
1N!
0X!
#360000
07!
#365000
17!
1P!
0N!
#370000
07!
#375000
17!
1N!
0W!
#380000
07!
#385000
17!
0N!
#390000
07!
#395000
17!
1N!
0V!
#400000
07!
#405000
17!
0P!
0N!
#410000
07!
#415000
17!
1N!
0U!
#420000
07!
#425000
17!
0N!
#430000
07!
#435000
17!
1N!
0T!
#440000
07!
#445000
17!
1P!
0N!
#450000
07!
#455000
17!
1N!
0S!
#460000
07!
#465000
17!
0N!
#470000
07!
#475000
17!
1N!
1I!
1H!
1E!
1D!
0L!
0R!
#480000
07!
#485000
17!
1m
1l
1i
1h
#490000
07!
#495000
17!
#500000
07!
#505000
17!
#510000
07!
#515000
17!
1@!
1?!
1>!
1=!
1<!
1;!
1:!
19!
18!
#520000
07!
#525000
17!
0N!
1O!
1L!
08!
#530000
07!
#535000
17!
1N!
1a!
#540000
07!
#545000
17!
0N!
#550000
07!
#555000
17!
1N!
1`!
#560000
07!
#565000
17!
0P!
0N!
#570000
07!
#575000
17!
1N!
1_!
#580000
07!
#585000
17!
0N!
#590000
07!
#595000
17!
1N!
1^!
#600000
07!
#605000
17!
1P!
0N!
#610000
07!
#615000
17!
1N!
1]!
#620000
07!
#625000
17!
0N!
#630000
07!
#635000
17!
1N!
1\!
#640000
07!
#645000
17!
0P!
0N!
#650000
07!
#655000
17!
1N!
1[!
#660000
07!
#665000
17!
0N!
#670000
07!
#675000
17!
1N!
1K!
1J!
0I!
0H!
1G!
1F!
0E!
0D!
0L!
1Z!
#680000
07!
#685000
17!
1w
1v
1s
1r
#690000
07!
#695000
17!
#700000
07!
#705000
17!
#710000
07!
#715000
17!
18!
#720000
07!
#725000
17!
1P!
0N!
1L!
08!
#730000
07!
#735000
17!
1N!
#740000
07!
#745000
17!
0P!
0N!
#750000
07!
#755000
17!
1N!
#760000
07!
#765000
17!
1P!
0N!
#770000
07!
#775000
17!
1N!
#780000
07!
#785000
17!
0P!
0N!
#790000
07!
#795000
17!
1N!
#800000
07!
#805000
17!
0N!
#810000
07!
#815000
17!
1N!
#820000
07!
#825000
17!
0N!
#830000
07!
#835000
17!
1N!
#840000
07!
#845000
17!
0N!
#850000
07!
#855000
17!
1N!
#860000
07!
#865000
17!
0N!
#870000
07!
#875000
17!
1N!
0J!
1I!
0G!
0F!
0L!
0g!
0f!
0c!
0b!
1o!
1n!
1k!
1j!
1x!
1v!
1u!
1t!
1s!
1r!
#880000
07!
#885000
17!
1S
1[
1Z
1X
1T
0c
0`
0^
0\
1Q!
1!!
1}
0"!
#890000
07!
#895000
17!
0S
0Q!
1"!
#900000
07!
#905000
17!
#910000
07!
#915000
17!
#920000
07!
#925000
17!
#930000
07!
#935000
17!
#940000
07!
#945000
17!
#950000
07!
#955000
17!
#960000
07!
#965000
17!
#970000
07!
#975000
17!
#980000
07!
#985000
17!
#990000
07!
#995000
17!
#1000000
07!
#1005000
17!
0>!
0<!
0;!
0:!
18!
#1010000
07!
#1015000
17!
0N!
1L!
08!
#1020000
07!
#1025000
17!
1N!
1Y!
#1030000
07!
#1035000
17!
0N!
#1040000
07!
#1045000
17!
1N!
1X!
#1050000
07!
#1055000
17!
0N!
0O!
#1060000
07!
#1065000
17!
1N!
#1070000
07!
#1075000
17!
0N!
1O!
#1080000
07!
#1085000
17!
1N!
1V!
#1090000
07!
#1095000
17!
0N!
0O!
#1100000
07!
#1105000
17!
1N!
#1110000
07!
#1115000
17!
0N!
#1120000
07!
#1125000
17!
1N!
#1130000
07!
#1135000
17!
0N!
#1140000
07!
#1145000
17!
1N!
#1150000
07!
#1155000
17!
0N!
1O!
#1160000
07!
#1165000
17!
1N!
0K!
0I!
0L!
1R!
#1170000
07!
#1175000
17!
0m
0l
0i
0h
#1180000
07!
#1185000
17!
#1190000
07!
#1195000
17!
#1200000
07!
#1205000
17!
0@!
1>!
0=!
1<!
1:!
09!
18!
#1210000
07!
#1215000
17!
1P!
0N!
0O!
1L!
08!
#1220000
07!
#1225000
17!
1N!
0a!
#1230000
07!
#1235000
17!
0N!
1O!
#1240000
07!
#1245000
17!
1N!
#1250000
07!
#1255000
17!
0N!
#1260000
07!
#1265000
17!
1N!
#1270000
07!
#1275000
17!
0N!
0O!
#1280000
07!
#1285000
17!
1N!
0^!
#1290000
07!
#1295000
17!
0N!
1O!
#1300000
07!
#1305000
17!
1N!
#1310000
07!
#1315000
17!
0N!
0O!
#1320000
07!
#1325000
17!
1N!
0\!
#1330000
07!
#1335000
17!
0N!
1O!
#1340000
07!
#1345000
17!
1N!
#1350000
07!
#1355000
17!
0N!
0O!
#1360000
07!
#1365000
17!
1N!
1K!
1J!
1I!
1H!
1G!
1F!
1E!
1D!
0L!
0Z!
#1370000
07!
#1375000
17!
1u
1t
1q
1p
#1380000
07!
#1385000
17!
#1390000
07!
#1395000
17!
#1400000
07!
#1405000
17!
18!
#1410000
07!
#1415000
17!
0N!
1L!
08!
#1420000
07!
#1425000
17!
1N!
#1430000
07!
#1435000
17!
0N!
1O!
#1440000
07!
#1445000
17!
1N!
#1450000
07!
#1455000
17!
0N!
#1460000
07!
#1465000
17!
1N!
#1470000
07!
#1475000
17!
0N!
0O!
#1480000
07!
#1485000
17!
1N!
#1490000
07!
#1495000
17!
0N!
1O!
#1500000
07!
#1505000
17!
1N!
#1510000
07!
#1515000
17!
0N!
0O!
#1520000
07!
#1525000
17!
1N!
#1530000
07!
#1535000
17!
0N!
1O!
#1540000
07!
#1545000
17!
1N!
#1550000
07!
#1555000
17!
0N!
0O!
#1560000
07!
#1565000
17!
1N!
0L!
1h!
0l!
0x!
0t!
#1570000
07!
#1575000
17!
1S
1Q!
1~
1|
1{
1z
1y
1x
0"!
#1580000
07!
#1585000
17!
0S
0Q!
1"!
#1590000
07!
#1595000
17!
#1600000
07!
#1605000
17!
#1610000
07!
#1615000
17!
#1620000
07!
#1625000
17!
#1630000
07!
#1635000
17!
#1640000
07!
#1645000
17!
#1650000
07!
#1655000
17!
#1660000
07!
#1665000
17!
#1670000
07!
#1675000
17!
#1680000
07!
#1685000
17!
#1690000
07!
#1695000
17!
1@!
0>!
1=!
0<!
0:!
19!
18!
#1700000
07!
#1705000
17!
0P!
0N!
1O!
1L!
08!
#1710000
07!
#1715000
17!
1N!
#1720000
07!
#1725000
17!
1P!
0N!
#1730000
07!
#1735000
17!
1N!
#1740000
07!
#1745000
17!
0P!
0N!
0O!
#1750000
07!
#1755000
17!
1N!
#1760000
07!
#1765000
17!
0N!
1O!
#1770000
07!
#1775000
17!
1N!
#1780000
07!
#1785000
17!
0N!
0O!
#1790000
07!
#1795000
17!
1N!
#1800000
07!
#1805000
17!
0N!
#1810000
07!
#1815000
17!
1N!
#1820000
07!
#1825000
17!
0N!
#1830000
07!
#1835000
17!
1N!
#1840000
07!
#1845000
17!
0N!
1O!
#1850000
07!
#1855000
17!
1N!
0K!
0I!
0H!
0G!
0F!
0E!
0D!
0L!
#1860000
07!
#1865000
17!
1n
#1870000
07!
#1875000
17!
#1880000
07!
#1885000
17!
#1890000
07!
#1895000
17!
0@!
1>!
0=!
1<!
1:!
09!
18!
#1900000
07!
#1905000
17!
1P!
0N!
0O!
1L!
08!
#1910000
07!
#1915000
17!
1N!
#1920000
07!
#1925000
17!
0N!
1O!
#1930000
07!
#1935000
17!
1N!
#1940000
07!
#1945000
17!
0N!
#1950000
07!
#1955000
17!
1N!
#1960000
07!
#1965000
17!
0N!
0O!
#1970000
07!
#1975000
17!
1N!
#1980000
07!
